{
  "slug": "compton",
  "name": "ูููุจุชูู",
  "state": "ูุงููููุฑููุง",
  "language": "ar",
  "shortDescription": "ูุฏููุฉ ุบููุฉ ุจุงูุชุงุฑูุฎ ูุนุฑููุฉ ุจูุณุงููุงุชูุง ุงูุซูุงููุฉุ ูุฑูุญ ุงููุฌุชูุนุ ูุงููุดูุฏ ุงูุญุถุฑู ุงููุชุทูุฑ.",
  "fullDescription": "ูููุจุชูู ูู ูุฏููุฉ ูู ุฌููุจ ููุงุทุนุฉ ููุณ ุฃูุฌููุณ ูุนุฑููุฉ ุจุฌุฐูุฑูุง ุงูุซูุงููุฉ ุงูุนูููุฉุ ููุดูุฏ ุงููููู ุงูุญูููุ ููููุฉ ุงููุฌุชูุน ุงููููุฉ. ุจุงูุฑุบู ูู ุงูุชุญุฏูุงุชุ ุดูุฏุช ุงููุฏููุฉ ุฌููุฏุงู ูุฅุนุงุฏุฉ ุงูุฅุญูุงุก ุชุฑูุฒ ุนูู ุงูุณูุงูุฉ ุงูุนุงูุฉ ูุงูุชุนููู ูุงูุชูููุฉ ุงูุงูุชุตุงุฏูุฉ. ุชูุฏู ูููุจุชูู ุฃุญูุงุก ูุชููุนุฉ ูุญุฏุงุฆู ููุนุงููุงุช ุซูุงููุฉ ุชุญุชูู ุจุชุฑุงุซูุง. ููุง ุชููุฑ ูุตููุงู ุณููุงู ุฅูู ูุณุท ูุฏููุฉ ููุณ ุฃูุฌููุณ ูุงููุฏู ุงููุญูุทุฉ ุงูุฃุฎุฑูุ ููุง ูุฌุนููุง ุฌุฒุกูุง ูุงููุง ูู ุงููุณูุฌ ุงูุญุถุฑู ููููุทูุฉ.",
  "heroImage": "https://images.unsplash.com/photo-1506744038136-46273834b3fb?auto=format&fit=crop&w=1920&q=80",
  "heroImageAlt": "ููุธุฑ ุดุงุฑุน ูู ูููุจุชูู ูุน ุฌุฏุงุฑูุงุช ุญุถุฑูุฉ ูุฃุฌูุงุก ูุฌุชูุนูุฉ",
  "population": "95 ุฃูู+",
  "avgHomePrice": "450 ุฃูู ุฏููุงุฑ",
  "tags": [
    "ุงูุชุฑุงุซ ุงูุซูุงูู",
    "ุงููุฌุชูุน",
    "ุชุฌุฏูุฏ ุญุถุฑู"
  ],
  "neighborhoods": [
    {
      "name": "ุบุงุฑุฏููุง",
      "type": "ูุฏููุฉ",
      "slug": "gardena",
      "description": "ูุฏููุฉ ูุฌุงูุฑุฉ ูุนุฑููุฉ ุจุชููุน ุณูุงููุง ูููุงุทู ุงูุชุณูู.",
      "image": "https://images.unsplash.com/photo-1549924231-f129b911e442?auto=format&fit=crop&w=1920&q=80",
      "imageAlt": "ูุดูุฏ ุงูุดูุงุฑุน ุงูุญุถุฑูุฉ ูู ุบุงุฑุฏููุง",
      "distance": "4 ุฃููุงู ุฌููุจ ุบุฑุจ",
      "avgHomePrice": "600 ุฃูู ุฏููุงุฑ",
      "county": "ููุณ ุฃูุฌููุณ"
    },
    {
      "name": "ูุงุฑุณู",
      "type": "ูุฏููุฉ",
      "slug": "carson",
      "description": "ูุฏููุฉ ุชุฌูุน ุจูู ุงูููุงุทู ุงูุณูููุฉ ูุงูุตูุงุนูุฉุ ุชูุฏู ุญุฏุงุฆู ููุฑุงูู ูุญููุฉ.",
      "image": "https://images.unsplash.com/photo-1504384308090-c894fdcc538d?auto=format&fit=crop&w=1920&q=80",
      "imageAlt": "ูุดูุฏ ูุฏููุฉ ูุงุฑุณู",
      "distance": "6 ุฃููุงู ุฌููุจุงู",
      "avgHomePrice": "550 ุฃูู ุฏููุงุฑ",
      "county": "ููุณ ุฃูุฌููุณ"
    },
    {
      "name": "ูููุบ ุจูุชุด",
      "type": "ูุฏููุฉ",
      "slug": "long-beach",
      "description": "ูุฏููุฉ ุณุงุญููุฉ ุชุชููุฒ ุจูุงุฌูุฉ ุจุญุฑูุฉ ูุงุจุถุฉุ ููุนุงูู ุซูุงููุฉุ ูุฃุญูุงุก ูุชููุนุฉ.",
      "image": "https://images.unsplash.com/photo-1506744038136-46273834b3fb?auto=format&fit=crop&w=800&q=80",
      "imageAlt": "ููุธุฑ ูููุงุก ูููุบ ุจูุชุด",
      "distance": "10 ุฃููุงู ุฌููุจ ุบุฑุจ",
      "avgHomePrice": "700 ุฃูู ุฏููุงุฑ",
      "county": "ููุณ ุฃูุฌููุณ"
    }
  ],
  "highlights": [
    {
      "title": "ูููุฉ ูููุจุชูู",
      "description": "ูููุฉ ูุฌุชูุนูุฉ ุชููุฑ ุงูุชุนููู ููุฑุต ุงูุนูู ููุณูุงู.",
      "icon": "๐",
      "bgImage": "https://images.unsplash.com/photo-1520880867055-1e30d1cb001c?auto=format&fit=crop&w=1920&q=80",
      "bgImageAlt": "ุญุฑู ูููุฉ ูููุจุชูู"
    },
    {
      "title": "ููุชุฒู ุฏููููุบูุฒ",
      "description": "ููุชุฒู ูุฌุชูุนู ูุจูุฑ ูุถู ููุงุนุจ ุฑูุงุถูุฉ ูููุงุทู ูุนุจ ูููุงุทู ูุฒูุฉ.",
      "icon": "๐ณ",
      "bgImage": "https://images.unsplash.com/photo-1597262975002-c5c3b14bbd62?auto=format&fit=crop&w=1200&q=80",
      "bgImageAlt": "ูุณุงุญุฉ ููุชุฒู ููุชูุญุฉ ูุน ุฃุดุฌุงุฑ ูููุงุนุฏ"
    },
    {
      "title": "ูุณุงุฑ ุฏุฑุงุฌุงุช ูููุจุชูู ูุฑูู",
      "description": "ูุณุงุฑ ุดููุฑ ูุฑููุจ ุงูุฏุฑุงุฌุงุชุ ูุงูุฌุฑูุ ูุงููุดุงุทุงุช ุงูุฎุงุฑุฌูุฉ.",
      "icon": "๐ด",
      "bgImage": "https://images.unsplash.com/photo-1469474968028-56623f02e42e?auto=format&fit=crop&w=1200&q=80",
      "bgImageAlt": "ูุณุงุฑ ุฏุฑุงุฌุงุช ุจูุญุงุฐุงุฉ ุฌุฏูู ูุงุก"
    },
    {
      "title": "ูุณุท ุงููุฏููุฉ ุงูุชุงุฑูุฎู",
      "description": "ููุทูุฉ ุจูุง ุฌุฏุงุฑูุงุชุ ูุฃุนูุงู ูุญููุฉุ ููุนุงููุงุช ูุฌุชูุนูุฉ ุชุญุชูู ุจุชุฑุงุซ ูููุจุชูู.",
      "icon": "๐จ",
      "bgImage": "https://images.unsplash.com/photo-1488747279002-c8523379faaa?auto=format&fit=crop&w=1200&q=80",
      "bgImageAlt": "ูู ุงูุดุงุฑุน ูุงููุญูุงุช ูู ูุณุท ูุฏููุฉ ูููุจุชูู"
    }
  ],
  "faqs": [
    {
      "question": "ุจูุงุฐุง ุชุดุชูุฑ ูููุจุชููุ",
      "answer": "ูููุจุชูู ูุดููุฑุฉ ุจุชุฑุงุซูุง ุงูุซูุงููุ ุชุงุฑูุฎ ุงูููุณูููุ ููุฑููุฉ ุงููุฌุชูุน.",
      "category": "ููุท ุงูุญูุงุฉ"
    },
    {
      "question": "ููู ูู ุณูู ุงูุนูุงุฑุงุช ูู ูููุจุชููุ",
      "answer": "ุงูุณูู ููุณูุฑ ุงูุชูููุฉ ููุงุฑูุฉ ุจุงููุฏู ุงููุฌุงูุฑุฉุ ูุน ุงูุชูุงู ูุชุฒุงูุฏ ุจุณุจุจ ุฌููุฏ ุฅุนุงุฏุฉ ุงูุชุทููุฑ.",
      "category": "ุงูุนูุงุฑุงุช"
    },
    {
      "question": "ูุง ุงูุฐู ููููู ูุนูู ูู ูููุจุชููุ",
      "answer": "ุงุณุชูุชุน ุจุงูุญุฏุงุฆู ุงููุญููุฉุ ุงููุนุงููุงุช ุงููุฌุชูุนูุฉุ ุงููุนุงูู ุงูุซูุงููุฉุ ูุงุณุชูุดุงู ุงูุฌุฏุงุฑูุงุช ุงูุชุงุฑูุฎูุฉ ูู ูุณุท ุงููุฏููุฉ.",
      "category": "ููุท ุงูุญูุงุฉ"
    },
    {
      "question": "ููู ูู ุงูุชููู ูู ูููุจุชููุ",
      "answer": "ุชุฎุฏู ูููุจุชูู ุนุฏุฉ ุทุฑู ุณุฑูุนุฉ ุฑุฆูุณูุฉ ูุฎุทูุท ูุชุฑูุ ููุง ูููุฑ ูุตููุงู ุณููุงู ุฅูู ููุณ ุฃูุฌููุณ ููููุบ ุจูุชุด.",
      "category": "ุงูููู"
    }
  ],
  "seo": {
    "metaTitle": "ุนูุงุฑุงุช ูููุจุชูู CA ูููุท ุงูุญูุงุฉ | ุงูุชุฑุงุซ ุงูุซูุงูู ูุงููุฌุชูุน",
    "metaDescription": "ุงุณุชูุดู ุฃุญูุงุก ูููุจุชููุ ุฃุจุฑุฒ ูุนุงูููุง ุงูุซูุงููุฉุ ููุฑุต ุงูุนูุงุฑุงุช ูู ููุงุทุนุฉ ููุณ ุฃูุฌููุณ.",
    "keywords": "ุนูุงุฑุงุช ูููุจุชููุ ูุฌุชูุน ูููุจุชููุ ุงูุนูุด ูู ูููุจุชููุ ููุงุฒู ูููุจุชูู ููุจูุน",
    "ogTitle": "ุงูุชุดู ูููุจุชูู: ุงูุซูุงูุฉุ ุงููุฌุชูุนุ ูุงูุญูุงุฉ ุงูุญุถุฑูุฉ",
    "ogDescription": "ุงุนุซุฑ ุนูู ููุฒูู ูู ูููุจุชูู ูุน ุชุฑุงุซูุง ุงูุบููุ ุงูุญุฏุงุฆูุ ูุงูุฃุญูุงุก ุงููุชุฌุฏุฏุฉ.",
    "ogImage": "https://images.unsplash.com/photo-1506744038136-46273834b3fb?auto=format&fit=crop&w=1200&q=80",
    "ogImageAlt": "ุดุงุฑุน ุญุถุฑู ูู ูููุจุชูู ูุน ุฌุฏุงุฑูุงุช",
    "twitterCard": "summary_large_image"
  },
  "schema_markup": [
    {
      "@context": "https://schema.org",
      "@type": "WebPage",
      "name": "ูููุจุชูู",
      "description": "ุงุณุชูุดู ุงูุนูุงุฑุงุชุ ุงูุฃุญูุงุกุ ูุฃุจุฑุฒ ุงููุนุงูู ูู ูููุจุชููุ ูุงููููุฑููุง.",
      "url": "https://example.com/locations/compton",
      "image": {
        "@type": "ImageObject",
        "url": "https://images.unsplash.com/photo-1506744038136-46273834b3fb?auto=format&fit=crop&w=1200&q=80",
        "caption": "ููุธุฑ ุดุงุฑุน ูู ูููุจุชูู ูุน ุฌุฏุงุฑูุงุช ุญุถุฑูุฉ ูุฃุฌูุงุก ูุฌุชูุนูุฉ"
      },
      "inLanguage": "ar",
      "mainEntity": {
        "@type": "City",
        "name": "ูููุจุชูู",
        "address": {
          "@type": "PostalAddress",
          "addressRegion": "CA",
          "addressCountry": "ุงูููุงูุงุช ุงููุชุญุฏุฉ"
        }
      }
    },
    {
      "@context": "https://schema.org",
      "@type": "FAQPage",
      "mainEntity": [
        {
          "@type": "Question",
          "name": "ุจูุงุฐุง ุชุดุชูุฑ ูููุจุชููุ",
          "acceptedAnswer": {
            "@type": "Answer",
            "text": "ูููุจุชูู ูุดููุฑุฉ ุจุชุฑุงุซูุง ุงูุซูุงููุ ุชุงุฑูุฎ ุงูููุณูููุ ููุฑููุฉ ุงููุฌุชูุน."
          }
        },
        {
          "@type": "Question",
          "name": "ููู ูู ุณูู ุงูุนูุงุฑุงุช ูู ูููุจุชููุ",
          "acceptedAnswer": {
            "@type": "Answer",
            "text": "ุงูุณูู ููุณูุฑ ุงูุชูููุฉ ููุงุฑูุฉ ุจุงููุฏู ุงููุฌุงูุฑุฉุ ูุน ุงูุชูุงู ูุชุฒุงูุฏ ุจุณุจุจ ุฌููุฏ ุฅุนุงุฏุฉ ุงูุชุทููุฑ."
          }
        },
        {
          "@type": "Question",
          "name": "ูุง ุงูุฐู ููููู ูุนูู ูู ูููุจุชููุ",
          "acceptedAnswer": {
            "@type": "Answer",
            "text": "ุงุณุชูุชุน ุจุงูุญุฏุงุฆู ุงููุญููุฉุ ุงููุนุงููุงุช ุงููุฌุชูุนูุฉุ ุงููุนุงูู ุงูุซูุงููุฉุ ูุงุณุชูุดุงู ุงูุฌุฏุงุฑูุงุช ุงูุชุงุฑูุฎูุฉ ูู ูุณุท ุงููุฏููุฉ."
          }
        },
        {
          "@type": "Question",
          "name": "ููู ูู ุงูุชููู ูู ูููุจุชููุ",
          "acceptedAnswer": {
            "@type": "Answer",
            "text": "ุชุฎุฏู ูููุจุชูู ุนุฏุฉ ุทุฑู ุณุฑูุนุฉ ุฑุฆูุณูุฉ ูุฎุทูุท ูุชุฑูุ ููุง ูููุฑ ูุตููุงู ุณููุงู ุฅูู ููุณ ุฃูุฌููุณ ููููุบ ุจูุชุด."
          }
        }
      ]
    }
  ]
}