{
  "slug": "laguna-beach",
  "name": "ูุงุบููุง ุจูุชุด",
  "state": "ูุงููููุฑููุง",
  "language": "ar",
  "shortDescription": "ูุฏููุฉ ุณุงุญููุฉ ุฎูุงุจุฉ ุชุดุชูุฑ ุจูุฌุชูุนูุง ุงููููุ ุดูุงุทุฆูุงุ ูุงูุฅุทูุงูุงุช ุงูุจุญุฑูุฉ ุงูุฎูุงุจุฉ.",
  "fullDescription": "ุชุดุชูุฑ ูุงุบููุง ุจูุชุด ุจุณุงุญููุง ุงููุฐููุ ุงููุดูุฏ ุงูููู ุงููุงุจุถ ุจุงูุญูุงุฉุ ูุงููุฒูุฌ ุงููุฑูุฏ ุจูู ุงูุฌูุงู ุงูุทุจูุนู ูุงููุนุงูู ุงูุซูุงููุฉ. ูุน ุดูุงุทุฆูุง ุงููููุฉุ ุฃุญูุงุถ ุงููุฏ ูุงูุฌุฒุฑุ ููุณุงุฑุงุช ุงูุชูุฒูุ ุชููุฑ ูุฐู ุงููุฏููุฉ ููุท ุญูุงุฉ ูุงุฏุฆ ูุฃููู. ูุณุชูุชุน ุงูุฒูุงุฑ ูุงูุณูุงู ุจูุนุงุฑุถ ุงูููุ ุงูููุฑุฌุงูุงุช ุงูุณูููุฉุ ูุงููุทุงุนู ุงูุฑุงููุฉุ ููุง ูุฌุนู ูุงุบููุง ุจูุชุด ูุฌูุฉ ูุฑุบูุจุฉ ูู ููุงุทุนุฉ ุฃูุฑุงูุฌ ููุนูุด ูุงูุฅุฌุงุฒุงุช.",
  "heroImage": "https://images.unsplash.com/photo-1506744038136-46273834b3fb?auto=format&fit=crop&w=1920&q=80",
  "heroImageAlt": "ุณุงุญู ุฎูุงุจ ูููุญุฏุฑุงุช ูู ูุงุบููุง ุจูุชุด",
  "population": "23 ุฃูู+",
  "avgHomePrice": "$3.5 ููููู",
  "tags": [
    "ุณุงุญููุฉ",
    "ุงููููู ูุงูุซูุงูุฉ",
    "ุงูุชุฑููู ุงูุฎุงุฑุฌู"
  ],
  "neighborhoods": [
    {
      "name": "ุฃููุณู ูููุฎู",
      "type": "ูุฏููุฉ",
      "slug": "aliso-viejo",
      "description": "ูุฌุชูุน ูุฎุทุท ูุนุฑูู ุจุงูุญุฏุงุฆูุ ุงูุชุณููุ ูุงูุญูุงุฉ ุงูููุงุณุจุฉ ููุนุงุฆูุงุช.",
      "image": "https://images.unsplash.com/photo-1494526585095-c41746248156?auto=format&fit=crop&w=800&q=80",
      "imageAlt": "ููุชุฒู ุญู ุฃููุณู ูููุฎู",
      "distance": "7 ุฃููุงู ุดูุงู ุดุฑู",
      "avgHomePrice": "$950 ุฃูู",
      "county": "ุฃูุฑุงูุฌ"
    },
    {
      "name": "ุฏุงูุง ุจูููุช",
      "type": "ูุฏููุฉ",
      "slug": "dana-point",
      "description": "ูุฏููุฉ ุณุงุญููุฉ ูุน ูุงุฑููุงุ ุดูุงุทุฆุ ููุดุงูุฏุฉ ุงูุญูุชุงู.",
      "image": "https://images.unsplash.com/photo-1501594907352-04cda38ebc29?auto=format&fit=crop&w=800&q=80",
      "imageAlt": "ููุธุฑ ููููุงุก ุฏุงูุง ุจูููุช",
      "distance": "8 ุฃููุงู ุฌููุจ ุดุฑู",
      "avgHomePrice": "$1.2 ููููู",
      "county": "ุฃูุฑุงูุฌ"
    },
    {
      "name": "ูุงุบููุง ููุบูู",
      "type": "ูุฏููุฉ",
      "slug": "laguna-niguel",
      "description": "ูุฌุชูุน ุณููู ุจู ุญุฏุงุฆูุ ูุฑุงูุฒ ุชุณููุ ูููุนุจ ุฌููู.",
      "image": "https://images.unsplash.com/photo-1524995997946-a1c2e315a42f?auto=format&fit=crop&w=800&q=80",
      "imageAlt": "ุญู ุถุงุญูุฉ ูู ูุงุบููุง ููุบูู",
      "distance": "9 ุฃููุงู ุดุฑู",
      "avgHomePrice": "$1.1 ููููู",
      "county": "ุฃูุฑุงูุฌ"
    },
    {
      "name": "ุณุงู ููููููุชู",
      "type": "ูุฏููุฉ",
      "slug": "san-clemente",
      "description": "ูุฏููุฉ ุณุงุญููุฉ ูุนุฑููุฉ ุจุฑุตูููุงุ ุดูุงุทุฆูุงุ ูุงูุนูุงุฑุฉ ุฐุงุช ุงูุทุฑุงุฒ ุงูุฅุณุจุงูู.",
      "image": "https://images.unsplash.com/photo-1504384308090-c894fdcc538d?auto=format&fit=crop&w=800&q=80",
      "imageAlt": "ุฑุตูู ุณุงู ููููููุชู ุนูุฏ ุงูุบุฑูุจ",
      "distance": "14 ููู ุฌููุจ ุดุฑู",
      "avgHomePrice": "$1.0 ููููู",
      "county": "ุฃูุฑุงูุฌ"
    }
  ],
  "highlights": [
    {
      "title": "ุงูุดูุงุทุฆ ูุฃุญูุงุถ ุงููุฏ ูุงูุฌุฒุฑ",
      "description": "ุดูุงุทุฆ ุฑูููุฉ ุฌูููุฉ ูุฃุญูุงุถ ูุฏ ูุฌุฒุฑ ูุซุงููุฉ ูุงุณุชูุดุงู ุงูุญูุงุฉ ุงูุจุญุฑูุฉ.",
      "icon": "๐๏ธ",
      "bgImage": "https://images.unsplash.com/photo-1506744038136-46273834b3fb?auto=format&fit=crop&w=1200&q=80",
      "bgImageAlt": "ุณุงุญู ูุงุบููุง ุจูุชุด ูุน ุฃุญูุงุถ ุงููุฏ ูุงูุฌุฒุฑ"
    },
    {
      "title": "ูุนุงุฑุถ ุงููู ูุงูููุฑุฌุงูุงุช",
      "description": "ูุดูุฏ ููู ูุงุจุถ ูุน ุงูุนุฏูุฏ ูู ุงููุนุงุฑุถ ูุงููุนุงููุงุช ุงูุณูููุฉ ูุซู ููุฑุฌุงู Pageant of the Masters.",
      "icon": "๐จ",
      "bgImage": "https://images.unsplash.com/photo-1494526585095-c41746248156?auto=format&fit=crop&w=1200&q=80",
      "bgImageAlt": "ุฏุงุฎู ูุนุฑุถ ูููู ูู ูุงุบููุง ุจูุชุด"
    },
    {
      "title": "ูุณุงุฑุงุช ุงูุชูุฒู",
      "description": "ูุณุงุฑุงุช ุฐุงุช ููุงุธุฑ ุทุจูุนูุฉ ูู ููุชุฒู ูุงุบููุง ููุณุช ูุงููุฏุฑููุณ ุงููุฑูุจ ุชููุฑ ุฅุทูุงูุงุช ุนูู ุงููุญูุท ููุฑุต ูุฑุคูุฉ ุงูุญูุงุฉ ุงูุจุฑูุฉ.",
      "icon": "๐ฅพ",
      "bgImage": "https://images.unsplash.com/photo-1501594907352-04cda38ebc29?auto=format&fit=crop&w=1200&q=80",
      "bgImageAlt": "ูุณุงุฑ ูุน ุฅุทูุงูุฉ ุนูู ุงููุญูุท ูู ููุชุฒู ูุงุบููุง ููุณุช ูุงููุฏุฑููุณ"
    },
    {
      "title": "ุงูููุงุทู ุงูุจุญุฑูุฉ ุงููุญููุฉ",
      "description": "ูุญููุงุช ุจุญุฑูุฉ ูุฎุตุตุฉ ูุญูุงูุฉ ุงูุญูุงุฉ ุงูุจุญุฑูุฉ ูุงููุญุงูุธุงุช ุงููุญููุฉ.",
      "icon": "๐",
      "bgImage": "https://images.unsplash.com/photo-1524995997946-a1c2e315a42f?auto=format&fit=crop&w=1200&q=80",
      "bgImageAlt": "ุญูุงุฉ ุจุญุฑูุฉ ุชุญุช ุงููุงุก ูุฑุจ ูุงุบููุง ุจูุชุด"
    }
  ],
  "faqs": [
    {
      "question": "ุจูุงุฐุง ุชุดุชูุฑ ูุงุบููุง ุจูุชุดุ",
      "answer": "ุชุดุชูุฑ ูุงุบููุง ุจูุชุด ุจุณุงุญููุง ุงูุฎูุงุจุ ูุฌุชูุนูุง ุงูููู ุงููุงุจุถ ุจุงูุญูุงุฉุ ุดูุงุทุฆูุงุ ูุงูุฃูุดุทุฉ ุงูุชุฑููููุฉ ุงูุฎุงุฑุฌูุฉ.",
      "category": "ุฃุณููุจ ุงูุญูุงุฉ"
    },
    {
      "question": "ููู ูู ุงููุฏุงุฑุณ ูู ูุงุบููุง ุจูุชุดุ",
      "answer": "ููุทูุฉ ูุฏุงุฑุณ ูุงุบููุง ุจูุชุด ุงูููุญุฏุฉ ุฐุงุช ุชุตููู ุนุงููุ ุชูุฏู ุชุนููููุง ุนุงููุง ููุชุงุฒูุง ูู ุงููุฑุญูุฉ ุงูุงุจุชุฏุงุฆูุฉ ุญุชู ุงูุซุงูููุฉ.",
      "category": "ุงูุชุนููู"
    },
    {
      "question": "ูุง ุงูุฃูุดุทุฉ ุงูุฎุงุฑุฌูุฉ ุงูุชู ูููููู ุงูุงุณุชูุชุงุน ุจูุง ูู ูุงุบููุง ุจูุชุดุ",
      "answer": "ููููู ุงูุงุณุชูุชุงุน ุจุฃูุดุทุฉ ุงูุดุงุทุฆุ ุงุณุชูุดุงู ุฃุญูุงุถ ุงููุฏ ูุงูุฌุฒุฑุ ุงูุชูุฒูุ ูุดุงูุฏุฉ ุงูุญูุชุงูุ ูุฒูุงุฑุฉ ููุฑุฌุงูุงุช ุงููู.",
      "category": "ุงูุชุฑููู"
    },
    {
      "question": "ููู ูู ุงูุชููู ูู ูุงุบููุง ุจูุชุดุ",
      "answer": "ุชููุฑ ูุงุบููุง ุจูุชุด ูุตููุงู ุณููุงู ุฅูู ุงูุทุฑู ุงูุณุฑูุนุฉ 73 ู405ุ ูุน ุฑุญูุงุช ููููุฉ ูููุฐุฌูุฉ ุฅูู ูุฏู ููุงุทุนุฉ ุฃูุฑุงูุฌ ุงููุฑูุจุฉ ูููุณ ุฃูุฌููุณ.",
      "category": "ุงูููู"
    }
  ],
  "seo": {
    "metaTitle": "ูุงุบููุง ุจูุชุด ูุงููููุฑููุง ุนูุงุฑุงุช ูุญูุงุฉ ุณุงุญููุฉ | ุงููููู ูุงูุชุฑููู ุงูุฎุงุฑุฌู",
    "metaDescription": "ุงูุชุดู ุฃุญูุงุก ูุงุบููุง ุจูุชุด ุงูุณุงุญููุฉุ ุงููุดูุฏ ุงููููุ ุงูุดูุงุทุฆุ ูุงูุฃูุดุทุฉ ุงูุฎุงุฑุฌูุฉ ูู ููุงุทุนุฉ ุฃูุฑุงูุฌ.",
    "keywords": "ุนูุงุฑุงุช ูุงุบููุง ุจูุชุดุ ููุงุฒู ุณุงุญููุฉ ูู ููุงุทุนุฉ ุฃูุฑุงูุฌุ ูููู ูุงุบููุง ุจูุชุดุ ุงูุนูุด ูู ูุงุบููุง ุจูุชุด",
    "ogTitle": "ุงุณุชูุดู ูุงุบููุง ุจูุชุด: ุฌูุงู ุณุงุญูู ููุฌุชูุน ููู ูุงุจุถ",
    "ogDescription": "ุงุฎุชุจุฑ ุดูุงุทุฆ ูุงุบููุง ุจูุชุด ุงูุฎูุงุจุฉุ ุงููุดูุฏ ุงูููู ุงููุฒุฏูุฑุ ูุงููุบุงูุฑุงุช ุงูุฎุงุฑุฌูุฉ ูู ููุงุทุนุฉ ุฃูุฑุงูุฌ.",
    "ogImage": "https://images.unsplash.com/photo-1506744038136-46273834b3fb?auto=format&fit=crop&w=1200&q=80",
    "ogImageAlt": "ุณุงุญู ูุงุบููุง ุจูุชุด ูุน ุฃุญูุงุถ ุงููุฏ ูุงูุฌุฒุฑ",
    "twitterCard": "summary_large_image"
  },
  "schema_markup": [
    {
      "@context": "https://schema.org",
      "@type": "WebPage",
      "name": "ูุงุบููุง ุจูุชุด",
      "description": "ุงุณุชูุดู ุงูุนูุงุฑุงุชุ ุงูุฃุญูุงุกุ ูุฃุจุฑุฒ ุงููุนุงูู ูู ูุงุบููุง ุจูุชุดุ ูุงููููุฑููุง.",
      "url": "https://example.com/locations/laguna-beach",
      "image": {
        "@type": "ImageObject",
        "url": "https://images.unsplash.com/photo-1506744038136-46273834b3fb?auto=format&fit=crop&w=1200&q=80",
        "caption": "ุณุงุญู ุฎูุงุจ ูููุญุฏุฑุงุช ูู ูุงุบููุง ุจูุชุด"
      },
      "inLanguage": "ar",
      "mainEntity": {
        "@type": "City",
        "name": "ูุงุบููุง ุจูุชุด",
        "address": {
          "@type": "PostalAddress",
          "addressRegion": "CA",
          "addressCountry": "USA"
        }
      }
    },
    {
      "@context": "https://schema.org",
      "@type": "FAQPage",
      "mainEntity": [
        {
          "@type": "Question",
          "name": "ุจูุงุฐุง ุชุดุชูุฑ ูุงุบููุง ุจูุชุดุ",
          "acceptedAnswer": {
            "@type": "Answer",
            "text": "ุชุดุชูุฑ ูุงุบููุง ุจูุชุด ุจุณุงุญููุง ุงูุฎูุงุจุ ูุฌุชูุนูุง ุงูููู ุงููุงุจุถ ุจุงูุญูุงุฉุ ุดูุงุทุฆูุงุ ูุงูุฃูุดุทุฉ ุงูุชุฑููููุฉ ุงูุฎุงุฑุฌูุฉ."
          }
        },
        {
          "@type": "Question",
          "name": "ููู ูู ุงููุฏุงุฑุณ ูู ูุงุบููุง ุจูุชุดุ",
          "acceptedAnswer": {
            "@type": "Answer",
            "text": "ููุทูุฉ ูุฏุงุฑุณ ูุงุบููุง ุจูุชุด ุงูููุญุฏุฉ ุฐุงุช ุชุตููู ุนุงููุ ุชูุฏู ุชุนููููุง ุนุงููุง ููุชุงุฒูุง ูู ุงููุฑุญูุฉ ุงูุงุจุชุฏุงุฆูุฉ ุญุชู ุงูุซุงูููุฉ."
          }
        },
        {
          "@type": "Question",
          "name": "ูุง ุงูุฃูุดุทุฉ ุงูุฎุงุฑุฌูุฉ ุงูุชู ูููููู ุงูุงุณุชูุชุงุน ุจูุง ูู ูุงุบููุง ุจูุชุดุ",
          "acceptedAnswer": {
            "@type": "Answer",
            "text": "ููููู ุงูุงุณุชูุชุงุน ุจุฃูุดุทุฉ ุงูุดุงุทุฆุ ุงุณุชูุดุงู ุฃุญูุงุถ ุงููุฏ ูุงูุฌุฒุฑุ ุงูุชูุฒูุ ูุดุงูุฏุฉ ุงูุญูุชุงูุ ูุฒูุงุฑุฉ ููุฑุฌุงูุงุช ุงููู."
          }
        },
        {
          "@type": "Question",
          "name": "ููู ูู ุงูุชููู ูู ูุงุบููุง ุจูุชุดุ",
          "acceptedAnswer": {
            "@type": "Answer",
            "text": "ุชููุฑ ูุงุบููุง ุจูุชุด ูุตููุงู ุณููุงู ุฅูู ุงูุทุฑู ุงูุณุฑูุนุฉ 73 ู405ุ ูุน ุฑุญูุงุช ููููุฉ ูููุฐุฌูุฉ ุฅูู ูุฏู ููุงุทุนุฉ ุฃูุฑุงูุฌ ุงููุฑูุจุฉ ูููุณ ุฃูุฌููุณ."
          }
        }
      ]
    }
  ]
}